Metadata-Version: 2.1
Name: gretta
Version: 0.0.1
Summary: Tensor-based SSA for sparse datasets with spatiotemporal information
Home-page: https://github.com/recspert/gretta
Author: Evgeny Frolov
License-File: LICENSE
Requires-Dist: numpy
Requires-Dist: scipy
Requires-Dist: pandas
Requires-Dist: numba
